pkg_stack/__init__.py
pkg_stack/mystack.py
pkg_stack/stack_exceptions.py
pkg_stack/stack_unittest.py
pkg_stack_skscodes-0.0.64.dist-info/LICENSE
pkg_stack_skscodes-0.0.64.dist-info/METADATA
pkg_stack_skscodes-0.0.64.dist-info/WHEEL
pkg_stack_skscodes-0.0.64.dist-info/top_level.txt
pkg_stack_skscodes-0.0.64.dist-info/RECORD
