Metadata-Version: 2.1
Name: pkg-stack-skscodes
Version: 0.0.64
Summary: It is documented package 'pkg_stack' which provides feature 'stack' functionality
Home-page: https://github.com/pypa/sampleproject
Author: suyog k sethia
Author-email: ssethia86@gmail.com
License: UNKNOWN
Platform: UNKNOWN
Classifier: Programming Language :: Python :: 3
Classifier: License :: OSI Approved :: MIT License
Classifier: Operating System :: OS Independent
